Metadata-Version: 1.1
Name: udc-dsnd-distributions
Version: 1.9
Summary: Gaussian and Binomial distributions
Home-page: UNKNOWN
Author: Gaurav Ansal
Author-email: ansal.gaurav@gmail.com
License: UNKNOWN
Platform: UNKNOWN
Classifier: Programming Language :: Python :: 3
Classifier: License :: OSI Approved :: MIT License
Classifier: Operating System :: OS Independent
